ypmeteo/__init__.py
ypmeteo-1.0.1b1.dist-info/LICENSE
ypmeteo-1.0.1b1.dist-info/METADATA
ypmeteo-1.0.1b1.dist-info/WHEEL
ypmeteo-1.0.1b1.dist-info/top_level.txt
ypmeteo-1.0.1b1.dist-info/RECORD
