Metadata-Version: 2.1
Name: ypmeteo
Version: 1.0.1b1
Summary: Read data from Yocto-Meteo module with pyusb
Author-email: Nathan Fraser <ndf-zz@6-v.org>
License: MIT
Project-URL: homepage, https://github.com/ndf-zz/ypmeteo
Keywords: yocto-meteo,pyusb
Classifier: Development Status :: 4 - Beta
Classifier: Programming Language :: Python :: 2
Classifier: Programming Language :: Python :: 3
Classifier: Operating System :: OS Independent
Classifier: Topic :: System :: Hardware :: Universal Serial Bus (USB) :: Miscellaneous
Requires-Python: >=2.7
License-File: LICENSE
Requires-Dist: pyusb
